pydicomutils/__init__.py
pydicomutils/IODs/BasicSRText.py
pydicomutils/IODs/CRImage.py
pydicomutils/IODs/CSPS.py
pydicomutils/IODs/CTImage.py
pydicomutils/IODs/Comprehensive3DSRTID1500.py
pydicomutils/IODs/EnhancedSRTID1500.py
pydicomutils/IODs/GSPS.py
pydicomutils/IODs/IOD.py
pydicomutils/IODs/KOS.py
pydicomutils/IODs/SCImage.py
pydicomutils/IODs/WSMImage.py
pydicomutils/IODs/__init__.py
pydicomutils/IODs/modules/__init__.py
pydicomutils/IODs/modules/general_modules.py
pydicomutils/IODs/modules/specific_image_modules.py
pydicomutils/IODs/modules/specific_presentation_state_modules.py
pydicomutils/IODs/modules/specific_sr_modules.py
pydicomutils/IODs/sequences/Sequences.py
pydicomutils/IODs/sequences/__init__.py
pydicomutils/external/__init__.py
pydicomutils/external/icc_profiles/__init__.py
pydicomutils/external/icc_profiles/icc_profiles.py
pydicomutils/external/icc_profiles/sRGB2014.icc
pydicomutils-0.2.2.dist-info/LICENSE
pydicomutils-0.2.2.dist-info/METADATA
pydicomutils-0.2.2.dist-info/WHEEL
pydicomutils-0.2.2.dist-info/top_level.txt
pydicomutils-0.2.2.dist-info/RECORD
