Metadata-Version: 2.2
Name: pydicomutils
Version: 0.2.2
Summary: Python library for creating DICOM objects
Author-email: Daniel Forsberg <daniel.forsberg@sectra.com>
License: Copyright 2020 Sectra AB
Project-URL: repository, https://github.com/sectra-medical/pydicomutils
Project-URL: documentation, https://github.com/sectra-medical/pydicomutils
Keywords: dicom,python
Classifier: License :: OSI Approved :: MIT License
Classifier: Programming Language :: Python
Classifier: Programming Language :: Python :: 3
Requires-Python: >=3.7
License-File: LICENSE
Requires-Dist: pydicom
Provides-Extra: build
Requires-Dist: build; extra == "build"
Requires-Dist: twine; extra == "build"
Provides-Extra: dev
Requires-Dist: black; extra == "dev"
Requires-Dist: bumpver; extra == "dev"
Requires-Dist: isort; extra == "dev"
Requires-Dist: mypy; extra == "dev"
Requires-Dist: pytest; extra == "dev"
